LICENSE.txt
MANIFEST.in
README.md
get_docker_secret.py
setup.py
get_docker_secret.egg-info/PKG-INFO
get_docker_secret.egg-info/SOURCES.txt
get_docker_secret.egg-info/dependency_links.txt
get_docker_secret.egg-info/top_level.txt