Metadata-Version: 2.1
Name: get-docker-secret
Version: 2.0.0
Summary: Utility function to fetch docker secrets/envvars.
Home-page: https://github.com/fischerfredl/get-docker-secret
Author: Alfred Melch
Author-email: dev@melch.pro
License: MIT
Keywords: docker,secret,envvar,config
Classifier: License :: OSI Approved :: MIT License
Classifier: Programming Language :: Python :: 2.7
Classifier: Programming Language :: Python :: 3.6
Classifier: Programming Language :: Python :: 3.7
Classifier: Programming Language :: Python :: 3.8
Classifier: Programming Language :: Python :: 3.9
Classifier: Programming Language :: Python :: 3.10
Classifier: Programming Language :: Python :: 3.11
License-File: LICENSE.txt
